[
    {
      "title": "Breakthrough Message 1",
      "day": 26,
      "month": "January",
      "year": 2024,
      "link": "audio1.mp3"
    },
    {
      "title": "Breakthrough Message 2",
      "day": 2,
      "month": "February",
      "year": 2024,
      "link": "audio2.mp3"
    },
    {
      "title": "Breakthrough Message 3",
      "day": 15,
      "month": "March",
      "year": 2024,
      "link": "audio3.mp3"
    },
    {
      "title": "Breakthrough Message 4",
      "day": 10,
      "month": "April",
      "year": 2024,
      "link": "audio4.mp3"
    },
    {
      "title": "Breakthrough Message 5",
      "day": 5,
      "month": "May",
      "year": 2024,
      "link": "audio5.mp3"
    }
  ]
  